<phonebook>
	<human name="Boghena Feliksovna Ageykina">
		<phone>98588313482295</phone>
		<phone>140411439997</phone>
		<phone>8364808641</phone>
		<phone>904948993860302</phone>
		<phone>35</phone>
		<phone>696</phone>
		<phone>97337</phone>
		<phone>27827</phone>
	</human>
	<human name="Ulla Semenovna Aspidova">
		<phone>419765718070</phone>
		<phone>605794826340</phone>
		<phone>286897637870</phone>
		<phone>81472339267</phone>
		<phone>1008237</phone>
		<phone>6469542197</phone>
		<phone>7484141283</phone>
		<phone>06477750396100087</phone>
		<phone>4341992725</phone>
		<phone>69907781336508872</phone>
	</human>
	<human name="Aziza Danilovna Batrutdinova">
		<phone>63851657</phone>
		<phone>536017</phone>
		<phone>0102578411981207030</phone>
		<phone>816379375238998175</phone>
		<phone>080</phone>
	</human>
	<human name="Ioanna Tarasovna Boykova">
		<phone>032681474036637</phone>
		<phone>2267085282918730</phone>
		<phone>04064883670439167524</phone>
	</human>
	<human name="Anisiya Evgenyevna Boykova">
		<phone>07900113593370640</phone>
		<phone>9365</phone>
		<phone>869</phone>
		<phone>49185744478</phone>
		<phone>51786076521239546892</phone>
		<phone>1447</phone>
	</human>
	<human name="Emi Alekseevna Buryakova">
		<phone>6</phone>
		<phone>3366178125989285</phone>
		<phone>3</phone>
		<phone>2548486310</phone>
		<phone>5150751443122238</phone>
		<phone>7541</phone>
	</human>
	<human name="Gulynar Konstantinovna Caricyna">
		<phone>9970738781</phone>
		<phone>461831</phone>
		<phone>98807</phone>
		<phone>262920</phone>
		<phone>7981677699738801</phone>
		<phone>49355</phone>
	</human>
	<human name="Famary Vladislavovna Chuchanova">
		<phone>075</phone>
		<phone>41504</phone>
		<phone>0</phone>
		<phone>07863000700367</phone>
		<phone>864187572</phone>
		<phone>0345127004</phone>
		<phone>9075119</phone>
	</human>
	<human name="Alisa Valentinovna Chuchanova">
		<phone>86</phone>
		<phone>2658</phone>
		<phone>42342278135535116183</phone>
		<phone>92918383489</phone>
		<phone>79638</phone>
		<phone>410289545858462092</phone>
		<phone>40979</phone>
		<phone>295338712019031330</phone>
		<phone>5</phone>
	</human>
	<human name="Ghaklin Antonovna Chupova">
		<phone>17401159807</phone>
		<phone>26064672941556</phone>
		<phone>52513</phone>
		<phone>932692905914369359</phone>
		<phone>05685</phone>
		<phone>630055768799871</phone>
		<phone>3303400977437625</phone>
	</human>
	<human name="Irina Vyacheslavovna Citnikova">
		<phone>516</phone>
		<phone>21911</phone>
		<phone>58038229477</phone>
	</human>
	<human name="Antonina Ilyinichna Davydkina">
		<phone>2748211</phone>
		<phone>893126286836</phone>
		<phone>77152</phone>
		<phone>014791</phone>
		<phone>418</phone>
		<phone>405652122518323</phone>
		<phone>9386928323270884716</phone>
		<phone>41211581723484434</phone>
		<phone>9834103270268</phone>
	</human>
	<human name="Antonina Vasilyevna Delova">
		<phone>3926546512285</phone>
		<phone>859</phone>
		<phone>5159503728</phone>
		<phone>71426318865702</phone>
		<phone>38613354547</phone>
		<phone>1889023557</phone>
		<phone>495</phone>
		<phone>17694571732116</phone>
	</human>
	<human name="Arna Ilyinichna Emelina">
		<phone>356003694</phone>
		<phone>7413844456</phone>
		<phone>738032251441</phone>
		<phone>65930347320535</phone>
		<phone>5434198018750074</phone>
	</human>
	<human name="Alisa Eduardovna Ershova">
		<phone>789192641</phone>
		<phone>02770675408716534</phone>
		<phone>9</phone>
		<phone>80487381991</phone>
		<phone>37447221745764</phone>
		<phone>7256009523695472</phone>
		<phone>690058266598781</phone>
		<phone>94416437082086510</phone>
		<phone>6014</phone>
	</human>
	<human name="Sheyla Eduardovna Fanina">
		<phone>249636733868</phone>
		<phone>99010</phone>
		<phone>1408578722608834</phone>
		<phone>1883396786029966</phone>
		<phone>82779</phone>
	</human>
	<human name="Milena Georgievna Fedchenkova">
		<phone>6386191900566866660</phone>
	</human>
	<human name="Famary Kirillovna Ghukova">
		<phone>845197489148002</phone>
		<phone>1</phone>
		<phone>283124718970294</phone>
	</human>
	<human name="Aziza Stepanovna Kazarezova">
		<phone>0284152916</phone>
	</human>
	<human name="Zulyfiya Grigoryevna Klimushina">
		<phone>27272</phone>
		<phone>3920</phone>
		<phone>052</phone>
		<phone>9786</phone>
		<phone>2710980712305503</phone>
		<phone>8310295</phone>
		<phone>7807892259995</phone>
	</human>
	<human name="Mod Danilovna Kolesnikova">
		<phone>666020954077831</phone>
		<phone>5</phone>
		<phone>250394244126025787</phone>
	</human>
	<human name="Iuliya Anatolyevna Komzina">
		<phone>4632683698983</phone>
		<phone>85169208112652</phone>
		<phone>5391437566035</phone>
		<phone>699484</phone>
		<phone>1413</phone>
	</human>
	<human name="Konstanciya Yuryevna Korchagina">
		<phone>5178</phone>
		<phone>875790987</phone>
		<phone>10477</phone>
		<phone>8131721</phone>
		<phone>7819</phone>
		<phone>7342843603313</phone>
		<phone>611428564997771</phone>
		<phone>53</phone>
		<phone>2260069947779653</phone>
		<phone>516967</phone>
	</human>
	<human name="Raisa Lyvovna Kovalevskaya">
		<phone>0350875218588144</phone>
	</human>
	<human name="Angelina Alekseevna Lachkova">
		<phone>8027710741368</phone>
		<phone>459136950495528</phone>
		<phone>35148416157302</phone>
		<phone>99464276448399931787</phone>
		<phone>8</phone>
		<phone>29058662</phone>
		<phone>62017387</phone>
		<phone>9063824231288728</phone>
		<phone>3922</phone>
		<phone>69409240262</phone>
	</human>
	<human name="Yaroslava Ilyinichna Lipina">
		<phone>42170514126</phone>
		<phone>05943716747356883420</phone>
		<phone>0607635893066</phone>
		<phone>28953767859011150</phone>
		<phone>608107938278071</phone>
		<phone>856622849346608454</phone>
		<phone>9180714744992237</phone>
		<phone>13840872911</phone>
		<phone>79023066418339782556</phone>
	</human>
	<human name="Gulynar Semenovna Malinina">
		<phone>19990619</phone>
		<phone>57715187</phone>
	</human>
	<human name="Beata Lyvovna Nikolaeva">
		<phone>772152493826</phone>
		<phone>71904572444044013</phone>
		<phone>6450620237317</phone>
		<phone>4</phone>
	</human>
	<human name="Masha Leonidovna Novoselyceva">
		<phone>26969256811972</phone>
		<phone>387932</phone>
		<phone>7079</phone>
		<phone>6364552679</phone>
	</human>
	<human name="Feba Fedorovna Ogorodnikova">
		<phone>4971</phone>
		<phone>632</phone>
		<phone>84280882491639650</phone>
		<phone>613422344305502981</phone>
		<phone>8150977380738</phone>
		<phone>97</phone>
		<phone>292</phone>
		<phone>5010262424281</phone>
	</human>
	<human name="Rozario Lyvovna Pervak">
		<phone>004179483</phone>
		<phone>603841432480810</phone>
		<phone>50292609025</phone>
		<phone>4080081641188310448</phone>
		<phone>775096357</phone>
		<phone>537564909281454525</phone>
		<phone>96721557229</phone>
		<phone>7090495319839</phone>
	</human>
	<human name="Ninely Egorovna Pervak">
		<phone>7195</phone>
		<phone>51597927967827</phone>
		<phone>102686227937476590</phone>
		<phone>81102</phone>
		<phone>3</phone>
		<phone>092324599537</phone>
		<phone>435</phone>
	</human>
	<human name="Tatyyana Borisovna Pivovarova">
		<phone>45408778113</phone>
		<phone>762164481599536431</phone>
	</human>
	<human name="Galina Konstantinovna Pokrovskaya">
		<phone>0002447551834009</phone>
		<phone>8314874</phone>
		<phone>3395926</phone>
		<phone>8235966865749003625</phone>
		<phone>4028111924599533469</phone>
		<phone>491191137</phone>
		<phone>848032461</phone>
		<phone>0</phone>
		<phone>70117275097276</phone>
	</human>
	<human name="Marina Evgenyevna Pokrovskaya">
		<phone>77697544012740671</phone>
		<phone>9139879610260</phone>
		<phone>06831482317832</phone>
		<phone>8445868</phone>
		<phone>94594082831123</phone>
		<phone>4659713</phone>
		<phone>08808479515243531</phone>
		<phone>381618</phone>
	</human>
	<human name="Iuliya Efimovna Prihodyko">
		<phone>00203</phone>
		<phone>251999596588328</phone>
		<phone>21420</phone>
	</human>
	<human name="Antonina Grigoryevna Prihodyko">
		<phone>75411398950474098</phone>
		<phone>295051268735</phone>
	</human>
	<human name="Aelita Danilovna Prihodyko">
		<phone>837448</phone>
		<phone>449649</phone>
		<phone>4965378682616745577</phone>
		<phone>9798513242553286284</phone>
		<phone>408458332</phone>
		<phone>0992133479787518607</phone>
		<phone>03111172</phone>
		<phone>18358628</phone>
		<phone>46139633</phone>
	</human>
	<human name="Inna Fedorovna Ryabkova">
		<phone>2159867697907895</phone>
		<phone>71602373</phone>
	</human>
	<human name="Anushka Danilovna Rychenkova">
		<phone>67047159</phone>
	</human>
	<human name="Stella Efimovna Savrasova">
		<phone>890</phone>
		<phone>3288831365525</phone>
		<phone>11584386401529395950</phone>
		<phone>11758333471340482864</phone>
		<phone>5</phone>
		<phone>70848200214012576</phone>
		<phone>7396071344705399777</phone>
	</human>
	<human name="Adelaida Pavlovna Savrasova">
		<phone>256964310641</phone>
		<phone>3755842</phone>
		<phone>7660</phone>
		<phone>0885054451414860</phone>
		<phone>251335260193</phone>
	</human>
	<human name="Diana Romanovna Shakmakova">
		<phone>58739688</phone>
		<phone>96993780</phone>
		<phone>9</phone>
	</human>
	<human name="Elyvira Genadievna Skorobogatova">
		<phone>25262090703038481</phone>
		<phone>794160762</phone>
		<phone>6</phone>
		<phone>106453985</phone>
		<phone>4553670850177</phone>
		<phone>97403470</phone>
	</human>
	<human name="Elyvira Feliksovna Solodnikova">
		<phone>9735364188</phone>
		<phone>334546</phone>
		<phone>877146966642777</phone>
		<phone>049683704</phone>
		<phone>824235483</phone>
		<phone>474699</phone>
	</human>
	<human name="Yasna Olegovna Solomina">
		<phone>3417146034752905</phone>
		<phone>054370900</phone>
		<phone>817</phone>
		<phone>06514020455295</phone>
		<phone>9911616223896</phone>
		<phone>26185</phone>
		<phone>72182727</phone>
	</human>
	<human name="Eva Valeryevna Stepankova">
		<phone>98</phone>
		<phone>09320752954854898941</phone>
		<phone>81141838042728061</phone>
		<phone>7446028873132409</phone>
		<phone>2429</phone>
		<phone>12999171824368933</phone>
		<phone>30294652979704493991</phone>
		<phone>555</phone>
		<phone>0500367</phone>
		<phone>0172308860418704</phone>
	</human>
	<human name="Inna Eduardovna Stepashina">
		<phone>65387212299</phone>
		<phone>9069312222693343286</phone>
		<phone>1852824</phone>
		<phone>62298323</phone>
		<phone>82</phone>
	</human>
	<human name="Kseniya Evgenyevna Suvorkina">
		<phone>363</phone>
		<phone>732829106045521</phone>
		<phone>523237736</phone>
		<phone>452</phone>
		<phone>131770820064</phone>
	</human>
	<human name="Stefaniya Ivanovna Tihomirova">
		<phone>4709</phone>
		<phone>2535462577370353</phone>
		<phone>5589902386276481899</phone>
	</human>
	<human name="Ninely Arkadyevna Tyannikova">
		<phone>2066</phone>
		<phone>9989845721017740</phone>
		<phone>276876838374200</phone>
		<phone>2681185109511778</phone>
		<phone>769399378500</phone>
		<phone>775426753780780169</phone>
		<phone>9512472059</phone>
		<phone>96976</phone>
		<phone>35200101</phone>
	</human>
	<human name="Raisa Olegovna Tyushnyakova">
		<phone>65</phone>
		<phone>4594256089877</phone>
		<phone>93739556371</phone>
	</human>
    <human name="Mod Dmitrievna Tipalova">
        <phone>2069817603051200</phone>
    </human>
</phonebook>